setup.cfg
setup.py
bulbs/__init__.py
bulbs/__pycache__/__init__.cpython-35.pyc
bulbs/ads/__init__.py
bulbs/ads/middleware.py
bulbs/ads/models.py
bulbs/ads/urls.py
bulbs/ads/views.py
bulbs/ads/__pycache__/__init__.cpython-35.pyc
bulbs/ads/__pycache__/models.cpython-35.pyc
bulbs/ads/migrations/0001_initial.py
bulbs/ads/migrations/__init__.py
bulbs/ads/migrations/__pycache__/0001_initial.cpython-35.pyc
bulbs/ads/migrations/__pycache__/__init__.cpython-35.pyc
bulbs/ads/static/js/mobile-ad-placer.js
bulbs/ads/static/js/mobile-ad-placer.test.js
bulbs/ads/templates/ads/ads-targeting.html
bulbs/ads/templates/ads/dfp.html
bulbs/ads/templatetags/__init__.py
bulbs/ads/templatetags/ads.py
bulbs/ads/templatetags/__pycache__/__init__.cpython-35.pyc
bulbs/api/__init__.py
bulbs/api/metadata.py
bulbs/api/mixins.py
bulbs/api/permissions.py
bulbs/api/urls.py
bulbs/api/views.py
bulbs/api/__pycache__/__init__.cpython-35.pyc
bulbs/api/management/__init__.py
bulbs/api/management/__pycache__/__init__.cpython-35.pyc
bulbs/api/management/commands/__init__.py
bulbs/api/management/commands/create_app_authtoken.py
bulbs/api/migrations/0001_initial.py
bulbs/api/migrations/__init__.py
bulbs/api/migrations/__pycache__/0001_initial.cpython-35.pyc
bulbs/api/migrations/__pycache__/__init__.cpython-35.pyc
bulbs/api/templates/__bug_report_email.html
bulbs/api/templates/registration/logged_out.html
bulbs/campaigns/__init__.py
bulbs/campaigns/models.py
bulbs/campaigns/serializers.py
bulbs/campaigns/tasks.py
bulbs/campaigns/urls.py
bulbs/campaigns/views.py
bulbs/campaigns/__pycache__/__init__.cpython-35.pyc
bulbs/campaigns/__pycache__/models.cpython-35.pyc
bulbs/campaigns/__pycache__/tasks.cpython-35.pyc
bulbs/campaigns/migrations/0001_initial.py
bulbs/campaigns/migrations/0002_auto_20150318_1926.py
bulbs/campaigns/migrations/0003_auto_20150528_1434.py
bulbs/campaigns/migrations/0004_auto_20151103_1358.py
bulbs/campaigns/migrations/0005_campaign_tunic_campaign_id.py
django_bulbs.egg-info/PKG-INFO
django_bulbs.egg-info/SOURCES.txt
django_bulbs.egg-info/dependency_links.txt
django_bulbs.egg-info/requires.txt
django_bulbs.egg-info/top_level.txt