Metadata-Version: 1.0
Name: django-bulbs
Version: 3.25.0
Summary: America's Finest Namespace
Home-page: https://github.com/theonion/django-bulbs
Author: Chris Sinchok
Author-email: csinchok@theonion.com
License: BSD
Platform: UNKNOWN
